Workbook
Name aporte: APP!$D$19:$D$19
Name patrimonio: APP!$D$22:$D$22
Name qtd_anos: APP!$D$20:$D$20
Name rendimento_carteira: APP!$D$15:$D$15
Name salario: APP!$D$14:$D$14
Name sugestao_investimento: APP!$D$16:$D$16
Name taxa_mensal: APP!$D$21:$D$21

Sheet APP
B13: CONFIGURAÇÕES
B14: Salário | D14: 2000
B15: Rendimento Carteira | D15: 0.006
B16: Sugestãode Investimento (30%) | D16: =D14*30% -> 600
B18: INVESTIMENTO MENSAL
B19: Quanto investir por mês? | D19: 200
B20: Por quantos anos? | D20: 5
B21: Taxa de Rendimento Mensal? | D21: 0.01079
B22: Patrimônio acumulado? | D22: {=FV(taxa_mensal,qtd_anos*12,aporte*-1)} -> 16755.383
B23: Dividendos Mensais? | D23: {=patrimonio*rendimento_carteira} -> 100.5323
B25: Cenários | D25: Dividendo
A26: 2 | B26: Quanto em 2 anos? | C26: =FV($D$21,$A26*12,$D$19*-1) -> 5445.5255 | D26: {=$C26*rendimento_carteira} -> 32.673153
A27: 5 | B27: Quanto em 5 anos? | C27: =FV($D$21,$A27*12,$D$19*-1) -> 16755.383 | D27: {=$C27*rendimento_carteira} -> 100.5323
A28: 10 | B28: Quanto em 10 anos? | C28: =FV($D$21,$A28*12,$D$19*-1) -> 48656.843 | D28: {=$C28*rendimento_carteira} -> 291.94106
A29: 20 | B29: Quanto em 20 anos? | C29: =FV($D$21,$A29*12,$D$19*-1) -> 225039.68 | D29: {=$C29*rendimento_carteira} -> 1350.2381
A30: 30 | B30: Quanto em 30 anos? | C30: =FV($D$21,$A30*12,$D$19*-1) -> 864433.93 | D30: {=$C30*rendimento_carteira} -> 5186.6036
B34: Perfil | C34: Agressivo
B35: VALOR A SER INVESTIDO POR MÊS | C35: {=+aporte} -> 200
B37: TIPO DE FII | C37: Percentual Sugerido | D37: Valores
B38: PAPEL | C38: =VLOOKUP($C$34&"-"&B38,Planilha2!A:D,4,FALSE) -> 0.5 | D38: =C38*$C$35 -> 100
B39: TIJOLO | C39: =VLOOKUP($C$34&"-"&B39,Planilha2!A:D,4,FALSE) -> 0.1 | D39: =C39*$C$35 -> 20
B40: HÍBRIDOS | C40: =VLOOKUP($C$34&"-"&B40,Planilha2!A:D,4,FALSE) -> 0.05 | D40: =C40*$C$35 -> 10
B41: FOFs | C41: =VLOOKUP($C$34&"-"&B41,Planilha2!A:D,4,FALSE) -> 0.05 | D41: =C41*$C$35 -> 10
B42: DESENVOLVIMENTO | C42: =VLOOKUP($C$34&"-"&B42,Planilha2!A:D,4,FALSE) -> 0.2 | D42: =C42*$C$35 -> 40
B43: HOTELARIAS | C43: =VLOOKUP($C$34&"-"&B43,Planilha2!A:D,4,FALSE) -> 0.1 | D43: =C43*$C$35 -> 20
D44: =SUM(D38:D43) -> 200

Sheet Planilha2
A2: CHAVE | B2: Perfil | C2: TIPO DE FII | D2: %
A3: Conservador-PAPEL | B3: Conservador | C3: PAPEL | D3: 0.3 | H3: %
A4: Conservador-TIJOLO | B4: Conservador | C4: TIJOLO | D4: 0.5 | G4: Moderado-TIJOLO | H4: =VLOOKUP(G4,$A:$D,4,FALSE) -> 0.35
A5: Conservador-HÍBRIDOS | B5: Conservador | C5: HÍBRIDOS | D5: 0.1
A6: Conservador-FOFs | B6: Conservador | C6: FOFs | D6: 0.1
A7: Conservador-DESENVOLVIMENTO | B7: Conservador | C7: DESENVOLVIMENTO | D7: 0
A8: Conservador-HOTELARIAS | B8: Conservador | C8: HOTELARIAS | D8: 0
A9: Moderado-PAPEL | B9: Moderado | C9: PAPEL | D9: 0.32
A10: Moderado-TIJOLO | B10: Moderado | C10: TIJOLO | D10: 0.35
A11: Moderado-HÍBRIDOS | B11: Moderado | C11: HÍBRIDOS | D11: 0.08
A12: Moderado-FOFs | B12: Moderado | C12: FOFs | D12: 0.05
A13: Moderado-DESENVOLVIMENTO | B13: Moderado | C13: DESENVOLVIMENTO | D13: 0.1
A14: Moderado-HOTELARIAS | B14: Moderado | C14: HOTELARIAS | D14: 0.1
A15: Agressivo-PAPEL | B15: Agressivo | C15: PAPEL | D15: 0.5
A16: Agressivo-TIJOLO | B16: Agressivo | C16: TIJOLO | D16: 0.1
... A20: Agressivo-HOTELARIAS | B20: Agressivo | C20: HOTELARIAS | D20: 0.1
